Metadata-Version: 1.0
Name: thegeotarginator-back-interface
Version: 1.2.0
Summary: The contracts that TheGeotarginator-back has with 3rd parties.
Home-page: https://github.com/studyportals/thegeotarginator-back
Author: Studyportals
Author-email: lindy@studyportals.com
License: unlicense
Platform: UNKNOWN
